epyflu-0.2.6.dist-info/METADATA
epyflu-0.2.6.dist-info/WHEEL
epyflu-0.2.6.dist-info/entry_points.txt
epyflu-0.2.6.dist-info/licenses/LICENSE
epyflu/__init__.py
epyflu/bin/fluCLI
epyflu/cli.py
epyflu/gisaid_download.py
epyflu/gisaid_upload.py
epyflu/sqlite_db.py
epyflu-0.2.6.dist-info/RECORD
