Metadata-Version: 2.1
Name: epyflu
Version: 0.2.6
Summary: Upload to GISAID, record in local sqlite3 db, search/download GISAID to update released in local db
Author-Email: j3551ca <jessica.caleta@phac-aspc.gc.ca>
License: MIT
Project-URL: Docs, https://github.com/j3551ca/epyflu
Project-URL: Github, https://github.com/j3551ca/epyflu
Project-URL: Issues, https://github.com/j3551ca/epyflu/issues
Requires-Python: >=3.10
Requires-Dist: pandas>=2.2.2
